akxurl/__init__.py
akxurl/akxurl.py
akxurl-2.0.0.dist-info/LICENSE
akxurl-2.0.0.dist-info/METADATA
akxurl-2.0.0.dist-info/WHEEL
akxurl-2.0.0.dist-info/entry_points.txt
akxurl-2.0.0.dist-info/top_level.txt
akxurl-2.0.0.dist-info/RECORD
