Metadata-Version: 2.1
Name: akxurl
Version: 2.0.0
Summary: URL SHORTENER WITH PYTHON - 9 SERVER
Home-page: https://github.com/ITZAKX21
Author: AKXVAU
Author-email: dev.akxvau@gmail.com
License: MIT
Keywords: hacker,spam,tool,sms,bomber,call,prank,termux,hack,sms bomber,sms bomber,AKXVAU,URL,URL SHORTNER,AKXURL
Classifier: Development Status :: 4 - Beta
Classifier: Intended Audience :: Developers
Classifier: Topic :: Software Development :: Libraries :: Python Modules
Classifier: License :: OSI Approved :: MIT License
Classifier: Programming Language :: Python :: 3
Classifier: Operating System :: OS Independent
Classifier: Environment :: Console
Requires-Python: >=3.9
License-File: LICENSE
Requires-Dist: lolcat
Requires-Dist: requests
